periodic_simpletime.py
periodic_simpletime-1.0.4.dist-info/LICENSE
periodic_simpletime-1.0.4.dist-info/METADATA
periodic_simpletime-1.0.4.dist-info/WHEEL
periodic_simpletime-1.0.4.dist-info/top_level.txt
periodic_simpletime-1.0.4.dist-info/RECORD
