Metadata-Version: 2.1
Name: periodic-simpletime
Version: 1.0.4
Summary: A periodic event time management helper
Author-email: trueToastedCode <truetoastedcode@gmail.com>
Project-URL: Homepage, https://github.com/trueToastedCode/PeriodicSimpleTime
Project-URL: Bug Tracker, https://github.com/trueToastedCode/PeriodicSimpleTime/issues
Classifier: Programming Language :: Python :: 3
Classifier: License :: OSI Approved :: Apache Software License
Classifier: Operating System :: OS Independent
Requires-Python: >=3.7
License-File: LICENSE
